OpenLPOSCControl/__init__.py
OpenLPOSCControl/__main__.py
OpenLPOSCControl/openLPOSCControl.py
OpenLPOSCControl/OpenLPRestAPI/__init__.py
openlposccontrol-0.1.7.dist-info/entry_points.txt
openlposccontrol-0.1.7.dist-info/LICENSE
openlposccontrol-0.1.7.dist-info/WHEEL
openlposccontrol-0.1.7.dist-info/METADATA
openlposccontrol-0.1.7.dist-info/RECORD
